poetry_types/commands/__init__.py
poetry_types/commands/add_types.py
poetry_types/commands/base.py
poetry_types/commands/remove_types.py
poetry_types/commands/update_types.py
poetry_types/packages_map.py
poetry_types/poetry_types.py
poetry_types-0.6.0.dist-info/LICENSE
poetry_types-0.6.0.dist-info/METADATA
poetry_types-0.6.0.dist-info/WHEEL
poetry_types-0.6.0.dist-info/entry_points.txt
poetry_types-0.6.0.dist-info/RECORD
