Metadata-Version: 2.3
Name: poetry-types
Version: 0.6.0
Summary: A poetry plugin that adds/removes type stubs as dependencies like the mypy --install-types command.
Home-page: https://github.com/jvllmr/poetry-types
License: MIT
Author: Jan Vollmer
Author-email: jan@vllmr.dev
Requires-Python: >=3.9,<4.0
Classifier: License :: OSI Approved :: MIT License
Classifier: Natural Language :: English
Classifier: Operating System :: OS Independent
Classifier: Programming Language :: Python :: 3
Classifier: Programming Language :: Python :: 3.9
Classifier: Programming Language :: Python :: 3.10
Classifier: Programming Language :: Python :: 3.11
Classifier: Programming Language :: Python :: 3.12
Classifier: Programming Language :: Python :: 3.13
Requires-Dist: packaging (>=24.2)
Requires-Dist: poetry (>=2.0,<3.0)
Requires-Dist: tomlkit (>=0.13.2)
Project-URL: Repository, https://github.com/jvllmr/poetry-types
